LICENSE.txt
README.md
setup.cfg
setup.py
dropi/__init__.py
dropi/api.py
dropi/api_token.py
dropi/config.py
dropi.egg-info/PKG-INFO
dropi.egg-info/SOURCES.txt
dropi.egg-info/dependency_links.txt
dropi.egg-info/requires.txt
dropi.egg-info/top_level.txt