Metadata-Version: 2.1
Name: dropi
Version: 1.0.0
Summary: A (small) api connector library for 42's intranet
Home-page: https://github.com/42-Lisboa/dropi
Author: Pedro Mora - "drop"
Author-email: drop@42lisboa.com
License: UNKNOWN
Project-URL: Bug Tracker, https://github.com/42-Lisboa/dropi/issues
Platform: UNKNOWN
Classifier: Programming Language :: Python :: 3
Classifier: Operating System :: OS Independent
Requires-Python: >=3.10
License-File: LICENSE.txt
